outset/_OutsetGrid.py
outset/__init__.py
outset/_draw_marquee.py
outset/_inset_outsets.py
outset/_marqueeplot.py
outset/_auxlib/__init__.py
outset/_auxlib/align_marker_.py
outset/_auxlib/calc_aspect_.py
outset/_auxlib/calc_outer_pad_.py
outset/_auxlib/compose_callout_leader_.py
outset/_auxlib/draw_callout_.py
outset/_auxlib/draw_frame_.py
outset/_auxlib/equalize_aspect_.py
outset/_auxlib/find_intersection_.py
outset/_auxlib/get_vertices_extent_.py
outset/_auxlib/is_axes_unset_.py
outset/_auxlib/lighten_color_.py
outset/_auxlib/make_radial_gradient_.py
outset/_auxlib/minimal_perimeter_permutation_.py
outset/_auxlib/resize_figure_to_axes_.py
outset/_auxlib/robust_groupby_.py
outset/_auxlib/rotate_marker_.py
outset/_auxlib/set_aspect_.py
outset/mark/_MarkAlphabeticalBadges.py
outset/mark/_MarkArrow.py
outset/mark/_MarkInlaidAsterisk.py
outset/mark/_MarkMagnifyingGlass.py
outset/mark/_MarkNumericalBadges.py
outset/mark/_MarkRomanBadges.py
outset/mark/__init__.py
outset/patched/__init__.py
outset/patched/_annotateplot.py
outset/patched/_regplot.py
outset/patched/_scatterplot.py
outset/stub/_CalcBoundsIQR.py
outset/stub/__init__.py
outset/stub/_rescale_clip_outliers.py
outset/stub/_stub_all_clipped_values.py
outset/stub/_stub_edge_mark.py
outset/tweak/_TweakReflect.py
outset/tweak/_TweakSpreadArea.py
outset/tweak/__init__.py
outset/util/_NamedFrames.py
outset/util/_SplitKwarg.py
outset/util/__init__.py
outset/util/_layout_corner_insets.py
outset-0.1.9.dist-info/LICENSE
outset-0.1.9.dist-info/WHEEL
outset-0.1.9.dist-info/METADATA
outset-0.1.9.dist-info/RECORD
