Metadata-Version: 2.1
Name: outset
Version: 0.1.9
Summary: add zoom indicators, insets, and magnified panels to matplotlib/seaborn visualizations with ease!
Author-email: Matthew Andres Moreno <m.more500@gmail.com>
Requires-Python: >=3.8.1
Classifier: Development Status :: 3 - Alpha
Classifier: Intended Audience :: Developers
Classifier: License :: OSI Approved :: MIT License
Classifier: Programming Language :: Python :: 3 :: Only
Classifier: Programming Language :: Python :: 3.8
Classifier: Programming Language :: Python :: 3.9
Classifier: Programming Language :: Python :: 3.10
Classifier: Programming Language :: Python :: 3.11
Requires-Dist: adjusttext
Requires-Dist: frozendict
Requires-Dist: matplotlib
Requires-Dist: numpy
Requires-Dist: opytional
Requires-Dist: pandas
Requires-Dist: seaborn
Requires-Dist: pyspark>=3.0.0 ; extra == "spark"
Requires-Dist: bandit[toml]==1.7.6 ; extra == "test"
Requires-Dist: black==23.11.0 ; extra == "test"
Requires-Dist: check-manifest==0.49 ; extra == "test"
Requires-Dist: flake8-bugbear==23.12.2 ; extra == "test"
Requires-Dist: flake8-docstrings ; extra == "test"
Requires-Dist: flake8-formatter_junit_xml ; extra == "test"
Requires-Dist: flake8 ; extra == "test"
Requires-Dist: flake8-pyproject ; extra == "test"
Requires-Dist: keras==2.15.0 ; extra == "test"
Requires-Dist: pre-commit==3.6.0 ; extra == "test"
Requires-Dist: pylint==3.0.3 ; extra == "test"
Requires-Dist: pylint_junit ; extra == "test"
Requires-Dist: pytest-cov==4.1.0 ; extra == "test"
Requires-Dist: pytest-mock<3.12.1 ; extra == "test"
Requires-Dist: pytest-runner ; extra == "test"
Requires-Dist: pytest==7.4.3 ; extra == "test"
Requires-Dist: pytest-github-actions-annotate-failures ; extra == "test"
Requires-Dist: scikit-learn ; extra == "test"
Requires-Dist: shellcheck-py==0.9.0.6 ; extra == "test"
Requires-Dist: python-slugify ; extra == "test"
Requires-Dist: tensorflow ; extra == "test"
Project-URL: Documentation, https://mmore500.com/outset
Project-URL: Source, https://github.com/mmore500/outset
Project-URL: Tracker, https://github.com/mmore500/outset/issues
Provides-Extra: spark
Provides-Extra: test
